{
  "$ref": "#/definitions/reviews",
  "definitions": {
    "reviews": {
      "type": "object",
      "properties": {
        "title": {
          "type": "string"
        },
        "subtitle": {
          "type": "string"
        },
        "type": {
          "type": "string"
        },
        "image": {
          "type": "string"
        },
        "alt": {
          "type": "string"
        },
        "desc": {
          "type": "string"
        },
        "pubDate": {
          "anyOf": [
            {
              "type": "string",
              "format": "date-time"
            },
            {
              "type": "string",
              "format": "date"
            },
            {
              "type": "integer",
              "format": "unix-time"
            }
          ]
        },
        "$schema": {
          "type": "string"
        }
      },
      "required": [
        "title",
        "type",
        "desc"
      ],
      "additionalProperties": false
    }
  },
  "$schema": "http://json-schema.org/draft-07/schema#"
}